demo/__init__.py
demo/run.py
demo/tests/__init__.py
demo/tests/test_api.py
testapis/__init__.py
testapis/case.py
testapis/cli.py
testapis/request.py
testapis/scaffold.py
testapis/running/__init__.py
testapis/running/conf.yml
testapis/running/runner.py
testapis/testdata/__init__.py
testapis/testdata/data.py
testapis/utils/__init__.py
testapis/utils/allure_util.py
testapis/utils/common.py
testapis/utils/config.py
testapis/utils/des_util.py
testapis/utils/dingtalk.py
testapis/utils/excel.py
testapis/utils/exceptions.py
testapis/utils/log.py
testapis/utils/mail.py
testapis/utils/mysql_util.py
testapis/utils/pytest_util.py
testapis/utils/swagger_util.py
testapis-0.0.2.dist-info/METADATA
testapis-0.0.2.dist-info/WHEEL
testapis-0.0.2.dist-info/entry_points.txt
testapis-0.0.2.dist-info/top_level.txt
testapis-0.0.2.dist-info/RECORD
